losses.py
pipex_loss-0.1.0.dist-info/METADATA
pipex_loss-0.1.0.dist-info/WHEEL
pipex_loss-0.1.0.dist-info/top_level.txt
pipex_loss-0.1.0.dist-info/RECORD
